{
  "disclaimer": "Data sourced from exchangerate.host",
  "timestamp": "2025-11-27T12:17:03Z",
  "rates": {
    "AED": 3.672496,
    "AFN": 66.503587,
    "ALL": 83.247918,
    "AMD": 381.119614,
    "ANG": 1.790055,
    "AOA": 916.999786,
    "ARS": 1452.768902,
    "AUD": 1.53196,
    "AWG": 1.8025,
    "AZN": 1.702782,
    "BAM": 1.684604,
    "BBD": 2.008286,
    "BDT": 122.068761,
    "BGN": 1.68881,
    "BHD": 0.376994,
    "BIF": 2944.642073,
    "BMD": 1,
    "BND": 1.294413,
    "BOB": 6.911986,
    "BRL": 5.346199,
    "BSD": 0.99708,
    "BTC": 0.000010937957,
    "BTN": 89.314122,
    "BWP": 13.333448,
    "BYN": 3.405714,
    "BYR": 19600,
    "BZD": 2.005357,
    "CAD": 1.40423,
    "CDF": 2199.9998,
    "CHF": 0.805796,
    "CLF": 0.02363,
    "CLP": 927.000071,
    "CNY": 7.080401,
    "CNH": 7.080615,
    "COP": 3736.38,
    "CRC": 498.540039,
    "CUC": 1,
    "CUP": 26.5,
    "CVE": 95.49674,
    "CZK": 20.848603,
    "DJF": 177.563976,
    "DKK": 6.446704,
    "DOP": 62.403638,
    "DZD": 130.404964,
    "EGP": 47.620201,
    "ERN": 15,
    "ETB": 153.480909,
    "EUR": 0.86316,
    "FJD": 2.273297,
    "FKP": 0.756099,
    "GBP": 0.755805,
    "GEL": 2.701269,
    "GGP": 0.756099,
    "GHS": 11.125003,
    "GIP": 0.756099,
    "GMD": 72.999814,
    "GNF": 8661.573312,
    "GTQ": 7.66306,
    "GYD": 209.288359,
    "HKD": 7.77767,
    "HNL": 26.251733,
    "HRK": 6.503301,
    "HTG": 130.474853,
    "HUF": 329.259498,
    "IDR": 16653,
    "ILS": 3.278785,
    "IMP": 0.756099,
    "INR": 89.3895,
    "IQD": 1306.218427,
    "IRR": 42112.503419,
    "ISK": 127.219884,
    "JEP": 0.756099,
    "JMD": 159.699911,
    "JOD": 0.708983,
    "JPY": 156.306993,
    "KES": 129.703533,
    "KGS": 87.45017,
    "KHR": 3991.421115,
    "KMF": 425.49826,
    "KPW": 899.998942,
    "KRW": 1462.009776,
    "KWD": 0.30702,
    "KYD": 0.830886,
    "KZT": 517.083674,
    "LAK": 21650.487946,
    "LBP": 89301.544372,
    "LKR": 307.005228,
    "LRD": 177.502255,
    "LSL": 17.085591,
    "LTL": 2.95274,
    "LVL": 0.60489,
    "LYD": 5.436739,
    "MAD": 9.245012,
    "MDL": 16.981197,
    "MGA": 4475.490745,
    "MKD": 52.993794,
    "MMK": 2099.958048,
    "MNT": 3563.313284,
    "MOP": 7.987011,
    "MRU": 39.704907,
    "MUR": 46.090118,
    "MVR": 15.409418,
    "MWK": 1729.041594,
    "MXN": 18.34609,
    "MYR": 4.131978,
    "MZN": 63.902122,
    "NAD": 17.084708,
    "NGN": 1442.893403,
    "NIO": 36.692823,
    "NOK": 10.18135,
    "NPR": 142.445671,
    "NZD": 1.74949,
    "OMR": 0.384503,
    "PAB": 1.000389,
    "PEN": 3.362317,
    "PGK": 4.223981,
    "PHP": 58.76902,
    "PKR": 281.685458,
    "PLN": 3.64977,
    "PYG": 6975.081611,
    "QAR": 3.641099,
    "RON": 4.393499,
    "RSD": 101.317994,
    "RUB": 78.300691,
    "RWF": 1449.797156,
    "SAR": 3.751166,
    "SBD": 8.237372,
    "SCR": 13.960333,
    "SDG": 601.499529,
    "SEK": 9.488895,
    "SGD": 1.297925,
    "SHP": 0.750259,
    "SLE": 22.950108,
    "SLL": 20969.498139,
    "SOS": 568.824882,
    "SRD": 38.463979,
    "STD": 20697.981008,
    "STN": 21.10268,
    "SVC": 8.724,
    "SYP": 11056.900429,
    "SZL": 17.084557,
    "THB": 32.231022,
    "TJS": 9.277315,
    "TMT": 3.5,
    "TND": 2.93875,
    "TOP": 2.40776,
    "TRY": 42.44348,
    "TTD": 6.768361,
    "TWD": 31.351903,
    "TZS": 2462.500865,
    "UAH": 42.205445,
    "UGX": 3625.821448,
    "UYU": 39.749749,
    "UZS": 11902.823895,
    "VES": 243.26823,
    "VND": 26375.5,
    "VUV": 122.653097,
    "WST": 2.824884,
    "XAF": 564.997976,
    "XAG": 0.018723,
    "XAU": 0.000241,
    "XCD": 2.70255,
    "XCG": 1.796994,
    "XDR": 0.702676,
    "XOF": 564.997976,
    "XPF": 102.723119,
    "YER": 238.350061,
    "ZAR": 17.16359,
    "ZMK": 9001.193911,
    "ZMW": 22.833961,
    "ZWL": 321.999592,
    "USD": 1
  }
}
